[
  {
    "firstName": "Osman",
    "lastName": "Slay",
    "email": "osmanslay@mail.com",
    "phone": "05395390539",
    "company": "Merit Royal Diamond",
    "customerType": "Hotel Guest",
    "vehicleType": "Luxury Minibus",
    "transferType": "Intercity Ride",
    "pickupLocation": "Ercan International Airport",
    "dropoffLocation": "Lefkoşa (Nicosia) City Centre",
    "transferDate": "2026-01-17",
    "transferTime": "14:00",
    "flightNumber": "",
    "passengers": "",
    "notes": "",
    "status": "Completed",
    "city": "Lefkoşa",
    "address": "Lefkoşa, KKTC",
    "age": "29",
    "language": "English",
    "gender": "Male",
    "id": 1784208827777
  },
  {
    "firstName": "Berk",
    "lastName": "Fenk",
    "email": "berkfenk@mail.com",
    "phone": "05335330533",
    "company": "Merit Royal Diamond",
    "customerType": "Hotel Guest",
    "vehicleType": "Luxury Minibus",
    "transferType": "Intercity Ride",
    "pickupLocation": "Ercan International Airport",
    "dropoffLocation": "Lefkoşa (Nicosia) City Centre",
    "transferDate": "2026-05-08",
    "transferTime": "05:00",
    "flightNumber": "",
    "passengers": "",
    "notes": "",
    "status": "Completed",
    "city": "Gazimağusa",
    "address": "Gazimağusa, KKTC",
    "age": "36",
    "language": "Russian",
    "gender": "Male",
    "id": 1784208886744
  },
  {
    "firstName": "Doğuş",
    "lastName": "Macıhusa",
    "email": "dogusmacihusa@mail.com",
    "phone": "04114110411",
    "company": "Merit Royal Diamond",
    "customerType": "Hotel Guest",
    "vehicleType": "Luxury Minibus",
    "transferType": "Intercity Ride",
    "pickupLocation": "Girne (Kyrenia) City Centre",
    "dropoffLocation": "Lefkoşa (Nicosia) City Centre",
    "transferDate": "2026-07-11",
    "transferTime": "16:00",
    "flightNumber": "",
    "passengers": "",
    "notes": "",
    "status": "Completed",
    "city": "Lefke",
    "address": "Lefke, KKTC",
    "age": "63",
    "language": "Greek",
    "gender": "Male",
    "id": 1784208946352
  },
  {
    "firstName": "Hasan",
    "lastName": "Oğluşoför",
    "email": "hasanoglusofor@mail.com",
    "phone": "05625620562",
    "company": "Merit Royal Diamond",
    "customerType": "Hotel Guest",
    "vehicleType": "Luxury Minibus",
    "transferType": "Intercity Ride",
    "pickupLocation": "Ercan International Airport",
    "dropoffLocation": "Lefkoşa (Nicosia) City Centre",
    "transferDate": "2026-07-17",
    "transferTime": "04:09",
    "flightNumber": "",
    "passengers": "",
    "notes": "",
    "status": "Completed",
    "city": "Lefkoşa",
    "address": "Lefkoşa, KKTC",
    "age": "38",
    "language": "Turkish",
    "gender": "Male",
    "id": 1784209033336
  },
  {
    "firstName": "Defne ",
    "lastName": "Katalbaş",
    "email": "defnekatalbas@mail.com",
    "phone": "06726720672",
    "company": "",
    "customerType": "Individual VIP",
    "vehicleType": "Premium SUV",
    "transferType": "Airport Transfer",
    "pickupLocation": "Ercan International Airport",
    "dropoffLocation": "İskele (Trikomo)",
    "transferDate": "2026-07-03",
    "transferTime": "15:10",
    "flightNumber": "TK 1926",
    "passengers": "3",
    "notes": "",
    "status": "Completed",
    "city": "Gazimağusa",
    "address": "Gazimağusa, KKTC",
    "age": "43",
    "language": "Turkish",
    "gender": "Female",
    "id": 1784209108104
  },
  {
    "firstName": "Meral",
    "lastName": "Tevketoğlu",
    "email": "meraltevketoglu@mail.com",
    "phone": "08928920892",
    "company": "Acapulco Resort",
    "customerType": "Hotel Guest",
    "vehicleType": "Executive Sedan",
    "transferType": "Airport Transfer",
    "pickupLocation": "Ercan International Airport",
    "dropoffLocation": "Concorde Luxury Resort",
    "transferDate": "2027-04-22",
    "transferTime": "19:00",
    "flightNumber": "TK 7096",
    "passengers": "",
    "notes": "Please provide a child seat.",
    "status": "Confirmed",
    "city": "İskele",
    "address": "İskele, KKTC",
    "age": "51",
    "language": "Russian",
    "gender": "Female",
    "id": 1784209289360
  },
  {
    "firstName": "Kadir",
    "lastName": "Makkuş",
    "email": "kadirmakkus@mail.com",
    "phone": "09119110911",
    "company": "Concorde Luxury Resort",
    "customerType": "Hotel Guest",
    "vehicleType": "First Class Sedan",
    "transferType": "Airport Transfer",
    "pickupLocation": "Larnaca International Airport",
    "dropoffLocation": "Concorde Luxury Resort",
    "transferDate": "2025-09-25",
    "transferTime": "04:00",
    "flightNumber": "TK 5324",
    "passengers": "4",
    "notes": "",
    "status": "Cancelled",
    "city": "Güzelyurt",
    "address": "Güzelyurt, KKTC",
    "age": "21",
    "language": "Greek",
    "gender": "Male",
    "id": 1784209995312
  },
  {
    "firstName": "Alpay",
    "lastName": "Fah",
    "email": "alpayfah@mail.com",
    "phone": "03113110311",
    "company": "",
    "customerType": "Individual VIP",
    "vehicleType": "VIP Business Van",
    "transferType": "Hourly Chauffeur",
    "pickupLocation": "Girne (Kyrenia) City Centre",
    "dropoffLocation": "Lefkoşa (Nicosia) City Centre",
    "transferDate": "2026-01-16",
    "transferTime": "05:00",
    "flightNumber": "",
    "passengers": "",
    "notes": "",
    "status": "Completed",
    "city": "Girne",
    "address": "Girne, KKTC",
    "age": "44",
    "language": "Greek",
    "gender": "Male",
    "id": 1784272849868
  },
  {
    "firstName": "Belkan",
    "lastName": "Bozdirenç",
    "email": "belkanbozdirenc@mail.com",
    "phone": "06726720672",
    "company": "Elexus Hotel Resort",
    "customerType": "Hotel Guest",
    "vehicleType": "VIP Business Van",
    "transferType": "Event Logistics",
    "pickupLocation": "Paphos Airport",
    "dropoffLocation": "Elexus Hotel Resort",
    "transferDate": "2026-09-20",
    "transferTime": "18:00",
    "flightNumber": "",
    "passengers": "",
    "notes": "",
    "status": "Cancelled",
    "city": "İskele",
    "address": "İskele, KKTC",
    "age": "26",
    "language": "Russian",
    "gender": "Male",
    "id": 1784272896564
  },
  {
    "firstName": "İbrahim Halil",
    "lastName": "Yarık",
    "email": "halilyarik@mail.com",
    "phone": "09879870987",
    "company": "",
    "customerType": "Individual VIP",
    "vehicleType": "Luxury Minibus",
    "transferType": "Point to Point",
    "pickupLocation": "Ercan International Airport",
    "dropoffLocation": "Lefkoşa (Nicosia) City Centre",
    "transferDate": "2026-01-16",
    "transferTime": "10:00",
    "flightNumber": "",
    "passengers": "2",
    "notes": "Please provide a child seat.",
    "status": "Completed",
    "city": "İskele",
    "address": "İskele, KKTC",
    "age": "46",
    "language": "Turkish",
    "gender": "Male",
    "id": 1784272960956
  },
  {
    "firstName": "Vedat",
    "lastName": "Dozkıran",
    "email": "vedatdozkiran@mail.com",
    "phone": "04444440444",
    "company": "",
    "customerType": "Individual VIP",
    "vehicleType": "Luxury Minibus",
    "transferType": "Point to Point",
    "pickupLocation": "İskele (Trikomo)",
    "dropoffLocation": "Lefkoşa (Nicosia) City Centre",
    "transferDate": "2026-04-23",
    "transferTime": "20:00",
    "flightNumber": "",
    "passengers": "",
    "notes": "Do not ring the bell upon arrival.",
    "status": "Completed",
    "city": "Lefkoşa",
    "address": "Lefkoşa, KKTC",
    "age": "32",
    "language": "English",
    "gender": "Male",
    "id": 1784273016708
  },
  {
    "firstName": "Arda",
    "lastName": "Kahin",
    "email": "ardakahin@mail.com",
    "phone": "05425420542",
    "company": "",
    "customerType": "Individual VIP",
    "vehicleType": "VIP Business Van",
    "transferType": "Hourly Chauffeur",
    "pickupLocation": "Ercan International Airport",
    "dropoffLocation": "Girne (Kyrenia) City Centre",
    "transferDate": "2026-07-30",
    "transferTime": "18:00",
    "flightNumber": "",
    "passengers": "2",
    "notes": "",
    "status": "Confirmed",
    "city": "Girne",
    "address": "Girne, KKTC",
    "age": "23",
    "language": "Turkish",
    "gender": "Male",
    "id": 1784273076668
  },
  {
    "firstName": "Ahmet",
    "lastName": "Çelik",
    "email": "ahmetçelik@mail.com",
    "phone": "05368515052",
    "company": "",
    "customerType": "Individual VIP",
    "vehicleType": "VIP Business Van",
    "transferType": "Intercity Ride",
    "pickupLocation": "İskele (Trikomo)",
    "dropoffLocation": "Long Beach Area",
    "transferDate": "2026-11-07",
    "transferTime": "09:45",
    "flightNumber": "",
    "passengers": "1",
    "notes": "",
    "status": "Confirmed",
    "city": "İskele",
    "address": "İskele, KKTC",
    "age": "40",
    "language": "Turkish",
    "gender": "Male",
    "id": 1784273076669
  },
  {
    "firstName": "Esra",
    "lastName": "Doğan",
    "email": "esradoğan@mail.com",
    "phone": "05428037283",
    "company": "Lord's Palace Hotel",
    "customerType": "Hotel Guest",
    "vehicleType": "First Class Sedan",
    "transferType": "Point to Point",
    "pickupLocation": "Long Beach Area",
    "dropoffLocation": "Cratos Premium Hotel",
    "transferDate": "2026-08-18",
    "transferTime": "06:07",
    "flightNumber": "",
    "passengers": "2",
    "notes": "",
    "status": "Cancelled",
    "city": "Long",
    "address": "Long, KKTC",
    "age": "41",
    "language": "Turkish",
    "gender": "Female",
    "id": 1784273076670
  },
  {
    "firstName": "Fatma",
    "lastName": "Doğan",
    "email": "fatmadoğan@mail.com",
    "phone": "05455316574",
    "company": "",
    "customerType": "Individual VIP",
    "vehicleType": "First Class Sedan",
    "transferType": "Hourly Chauffeur",
    "pickupLocation": "Concorde Luxury Resort",
    "dropoffLocation": "Cratos Premium Hotel",
    "transferDate": "2026-09-17",
    "transferTime": "14:19",
    "flightNumber": "",
    "passengers": "2",
    "notes": "",
    "status": "Confirmed",
    "city": "Concorde",
    "address": "Concorde, KKTC",
    "age": "22",
    "language": "Turkish",
    "gender": "Female",
    "id": 1784273076671
  },
  {
    "firstName": "Volkan",
    "lastName": "Çelik",
    "email": "volkançelik@mail.com",
    "phone": "05445429128",
    "company": "",
    "customerType": "Individual VIP",
    "vehicleType": "First Class Sedan",
    "transferType": "Airport Transfer",
    "pickupLocation": "Lord's Palace Hotel",
    "dropoffLocation": "Ercan International Airport",
    "transferDate": "2026-07-13",
    "transferTime": "22:56",
    "flightNumber": "TK 6513",
    "passengers": "4",
    "notes": "",
    "status": "Completed",
    "city": "Lord's",
    "address": "Lord's, KKTC",
    "age": "52",
    "language": "English",
    "gender": "Male",
    "id": 1784273076672
  },
  {
    "firstName": "Eren",
    "lastName": "Doğan",
    "email": "erendoğan@mail.com",
    "phone": "05516817266",
    "company": "Concorde Luxury Resort",
    "customerType": "Hotel Guest",
    "vehicleType": "Luxury Minibus",
    "transferType": "Hourly Chauffeur",
    "pickupLocation": "Bafra Resort Area",
    "dropoffLocation": "Les Ambassadeurs",
    "transferDate": "2026-05-07",
    "transferTime": "12:40",
    "flightNumber": "",
    "passengers": "5",
    "notes": "",
    "status": "Completed",
    "city": "Bafra",
    "address": "Bafra, KKTC",
    "age": "49",
    "language": "Turkish",
    "gender": "Male",
    "id": 1784273076673
  },
  {
    "firstName": "Gizem",
    "lastName": "Aydın",
    "email": "gizemaydın@mail.com",
    "phone": "05314763551",
    "company": "Concorde Luxury Resort",
    "customerType": "Hotel Guest",
    "vehicleType": "First Class Sedan",
    "transferType": "Point to Point",
    "pickupLocation": "Long Beach Area",
    "dropoffLocation": "Kaya Palazzo Resort",
    "transferDate": "2026-07-08",
    "transferTime": "11:35",
    "flightNumber": "",
    "passengers": "5",
    "notes": "",
    "status": "Cancelled",
    "city": "Long",
    "address": "Long, KKTC",
    "age": "55",
    "language": "Turkish",
    "gender": "Female",
    "id": 1784273076674
  },
  {
    "firstName": "Mehmet",
    "lastName": "Demir",
    "email": "mehmetdemir@mail.com",
    "phone": "05554099995",
    "company": "",
    "customerType": "Individual VIP",
    "vehicleType": "Luxury Minibus",
    "transferType": "Point to Point",
    "pickupLocation": "Kaya Palazzo Resort",
    "dropoffLocation": "Cratos Premium Hotel",
    "transferDate": "2026-08-27",
    "transferTime": "21:55",
    "flightNumber": "",
    "passengers": "5",
    "notes": "",
    "status": "Confirmed",
    "city": "Kaya",
    "address": "Kaya, KKTC",
    "age": "50",
    "language": "Turkish",
    "gender": "Male",
    "id": 1784273076675
  },
  {
    "firstName": "Kaan",
    "lastName": "Çetin",
    "email": "kaançetin@mail.com",
    "phone": "05571535104",
    "company": "",
    "customerType": "Individual VIP",
    "vehicleType": "VIP Business Van",
    "transferType": "Point to Point",
    "pickupLocation": "Lord's Palace Hotel",
    "dropoffLocation": "Bafra Resort Area",
    "transferDate": "2026-10-11",
    "transferTime": "09:55",
    "flightNumber": "",
    "passengers": "4",
    "notes": "",
    "status": "Cancelled",
    "city": "Lord's",
    "address": "Lord's, KKTC",
    "age": "29",
    "language": "English",
    "gender": "Male",
    "id": 1784273076676
  },
  {
    "firstName": "Esra",
    "lastName": "Çetin",
    "email": "esraçetin@mail.com",
    "phone": "05509787059",
    "company": "Concorde Luxury Resort",
    "customerType": "Hotel Guest",
    "vehicleType": "First Class Sedan",
    "transferType": "Event Logistics",
    "pickupLocation": "Gazimağusa (Famagusta) City Centre",
    "dropoffLocation": "Concorde Luxury Resort",
    "transferDate": "2026-05-23",
    "transferTime": "02:57",
    "flightNumber": "",
    "passengers": "4",
    "notes": "VIP meet and greet at the gate.",
    "status": "Completed",
    "city": "Gazimağusa",
    "address": "Gazimağusa, KKTC",
    "age": "55",
    "language": "Turkish",
    "gender": "Female",
    "id": 1784273076677
  },
  {
    "firstName": "Merve",
    "lastName": "Öztürk",
    "email": "merveöztürk@mail.com",
    "phone": "05458583600",
    "company": "Limak Cyprus Deluxe",
    "customerType": "Hotel Guest",
    "vehicleType": "Executive Sedan",
    "transferType": "Point to Point",
    "pickupLocation": "Les Ambassadeurs",
    "dropoffLocation": "Arkın Iskele Hotel",
    "transferDate": "2026-07-10",
    "transferTime": "21:48",
    "flightNumber": "",
    "passengers": "4",
    "notes": "Guest requested cold water and daily newspaper.",
    "status": "Completed",
    "city": "Les",
    "address": "Les, KKTC",
    "age": "34",
    "language": "English",
    "gender": "Female",
    "id": 1784273076678
  },
  {
    "firstName": "Ali",
    "lastName": "Demir",
    "email": "alidemir@mail.com",
    "phone": "05587824279",
    "company": "",
    "customerType": "Individual VIP",
    "vehicleType": "Executive Sedan",
    "transferType": "Point to Point",
    "pickupLocation": "Kaya Palazzo Resort",
    "dropoffLocation": "Bafra Resort Area",
    "transferDate": "2026-02-05",
    "transferTime": "07:34",
    "flightNumber": "",
    "passengers": "2",
    "notes": "",
    "status": "Cancelled",
    "city": "Kaya",
    "address": "Kaya, KKTC",
    "age": "54",
    "language": "Turkish",
    "gender": "Male",
    "id": 1784273076679
  },
  {
    "firstName": "Burak",
    "lastName": "Yılmaz",
    "email": "burakyılmaz@mail.com",
    "phone": "05524541651",
    "company": "",
    "customerType": "Individual VIP",
    "vehicleType": "VIP Business Van",
    "transferType": "Intercity Ride",
    "pickupLocation": "Kaya Palazzo Resort",
    "dropoffLocation": "Bafra Resort Area",
    "transferDate": "2026-06-04",
    "transferTime": "14:23",
    "flightNumber": "",
    "passengers": "4",
    "notes": "Fast track requested at the airport.",
    "status": "Completed",
    "city": "Kaya",
    "address": "Kaya, KKTC",
    "age": "52",
    "language": "English",
    "gender": "Male",
    "id": 1784273076680
  },
  {
    "firstName": "Murat",
    "lastName": "Yılmaz",
    "email": "muratyılmaz@mail.com",
    "phone": "05364488855",
    "company": "",
    "customerType": "Individual VIP",
    "vehicleType": "Luxury Minibus",
    "transferType": "Intercity Ride",
    "pickupLocation": "Cratos Premium Hotel",
    "dropoffLocation": "Gazimağusa (Famagusta) City Centre",
    "transferDate": "2026-06-04",
    "transferTime": "12:26",
    "flightNumber": "",
    "passengers": "3",
    "notes": "",
    "status": "Completed",
    "city": "Cratos",
    "address": "Cratos, KKTC",
    "age": "36",
    "language": "Turkish",
    "gender": "Male",
    "id": 1784273076681
  },
  {
    "firstName": "Berna",
    "lastName": "Kara",
    "email": "bernakara@mail.com",
    "phone": "05502888356",
    "company": "",
    "customerType": "Individual VIP",
    "vehicleType": "VIP Business Van",
    "transferType": "Intercity Ride",
    "pickupLocation": "Les Ambassadeurs",
    "dropoffLocation": "Acapulco Resort",
    "transferDate": "2026-06-24",
    "transferTime": "10:09",
    "flightNumber": "",
    "passengers": "5",
    "notes": "",
    "status": "Completed",
    "city": "Les",
    "address": "Les, KKTC",
    "age": "31",
    "language": "Turkish",
    "gender": "Female",
    "id": 1784273076682
  },
  {
    "firstName": "Ceren",
    "lastName": "Arslan",
    "email": "cerenarslan@mail.com",
    "phone": "05378859627",
    "company": "",
    "customerType": "Individual VIP",
    "vehicleType": "Executive Sedan",
    "transferType": "Hourly Chauffeur",
    "pickupLocation": "Cratos Premium Hotel",
    "dropoffLocation": "İskele (Trikomo)",
    "transferDate": "2026-04-22",
    "transferTime": "06:17",
    "flightNumber": "",
    "passengers": "3",
    "notes": "Guest has extra luggage, please assist.",
    "status": "Cancelled",
    "city": "Cratos",
    "address": "Cratos, KKTC",
    "age": "50",
    "language": "English",
    "gender": "Female",
    "id": 1784273076683
  },
  {
    "firstName": "Serkan",
    "lastName": "Şahin",
    "email": "serkanşahin@mail.com",
    "phone": "05331602856",
    "company": "Concorde Luxury Resort",
    "customerType": "Hotel Guest",
    "vehicleType": "Executive Sedan",
    "transferType": "Point to Point",
    "pickupLocation": "Lefkoşa (Nicosia) City Centre",
    "dropoffLocation": "Girne (Kyrenia) City Centre",
    "transferDate": "2026-09-17",
    "transferTime": "16:06",
    "flightNumber": "",
    "passengers": "5",
    "notes": "VIP meet and greet at the gate.",
    "status": "Confirmed",
    "city": "Lefkoşa",
    "address": "Lefkoşa, KKTC",
    "age": "22",
    "language": "English",
    "gender": "Male",
    "id": 1784273076684
  },
  {
    "firstName": "Ece",
    "lastName": "Yıldız",
    "email": "eceyıldız@mail.com",
    "phone": "05349737917",
    "company": "",
    "customerType": "Individual VIP",
    "vehicleType": "Luxury Minibus",
    "transferType": "Intercity Ride",
    "pickupLocation": "Bafra Resort Area",
    "dropoffLocation": "Gazimağusa (Famagusta) City Centre",
    "transferDate": "2026-11-20",
    "transferTime": "06:20",
    "flightNumber": "",
    "passengers": "5",
    "notes": "Requires wheelchair assistance.",
    "status": "Confirmed",
    "city": "Bafra",
    "address": "Bafra, KKTC",
    "age": "45",
    "language": "Turkish",
    "gender": "Female",
    "id": 1784273076685
  },
  {
    "firstName": "Gizem",
    "lastName": "Doğan",
    "email": "gizemdoğan@mail.com",
    "phone": "05383081043",
    "company": "",
    "customerType": "Individual VIP",
    "vehicleType": "Luxury Minibus",
    "transferType": "Hourly Chauffeur",
    "pickupLocation": "Acapulco Resort",
    "dropoffLocation": "İskele (Trikomo)",
    "transferDate": "2026-03-08",
    "transferTime": "12:54",
    "flightNumber": "",
    "passengers": "1",
    "notes": "",
    "status": "Completed",
    "city": "Acapulco",
    "address": "Acapulco, KKTC",
    "age": "49",
    "language": "Turkish",
    "gender": "Female",
    "id": 1784273076686
  },
  {
    "firstName": "Merve",
    "lastName": "Yıldız",
    "email": "merveyıldız@mail.com",
    "phone": "05352172956",
    "company": "",
    "customerType": "Individual VIP",
    "vehicleType": "Executive Sedan",
    "transferType": "Point to Point",
    "pickupLocation": "Merit Royal Diamond",
    "dropoffLocation": "Lord's Palace Hotel",
    "transferDate": "2026-04-18",
    "transferTime": "05:51",
    "flightNumber": "",
    "passengers": "3",
    "notes": "",
    "status": "Completed",
    "city": "Merit",
    "address": "Merit, KKTC",
    "age": "36",
    "language": "English",
    "gender": "Female",
    "id": 1784273076687
  },
  {
    "firstName": "Hasan",
    "lastName": "Özdemir",
    "email": "hasanözdemir@mail.com",
    "phone": "05499237840",
    "company": "",
    "customerType": "Individual VIP",
    "vehicleType": "VIP Business Van",
    "transferType": "Intercity Ride",
    "pickupLocation": "Bafra Resort Area",
    "dropoffLocation": "Arkın Iskele Hotel",
    "transferDate": "2026-03-11",
    "transferTime": "00:41",
    "flightNumber": "",
    "passengers": "5",
    "notes": "Guest requested cold water and daily newspaper.",
    "status": "Completed",
    "city": "Bafra",
    "address": "Bafra, KKTC",
    "age": "34",
    "language": "Turkish",
    "gender": "Male",
    "id": 1784273076688
  },
  {
    "firstName": "Hasan",
    "lastName": "Çelik",
    "email": "hasançelik@mail.com",
    "phone": "05312256368",
    "company": "Elexus Hotel Resort",
    "customerType": "Hotel Guest",
    "vehicleType": "Premium SUV",
    "transferType": "Intercity Ride",
    "pickupLocation": "Elexus Hotel Resort",
    "dropoffLocation": "Limak Cyprus Deluxe",
    "transferDate": "2026-08-21",
    "transferTime": "06:51",
    "flightNumber": "",
    "passengers": "4",
    "notes": "Fast track requested at the airport.",
    "status": "Confirmed",
    "city": "Elexus",
    "address": "Elexus, KKTC",
    "age": "43",
    "language": "Turkish",
    "gender": "Male",
    "id": 1784273076689
  },
  {
    "firstName": "Aslı",
    "lastName": "Çelik",
    "email": "aslıçelik@mail.com",
    "phone": "05477236739",
    "company": "Kaya Palazzo Resort",
    "customerType": "Hotel Guest",
    "vehicleType": "Executive Sedan",
    "transferType": "Hourly Chauffeur",
    "pickupLocation": "Bafra Resort Area",
    "dropoffLocation": "Lord's Palace Hotel",
    "transferDate": "2026-06-17",
    "transferTime": "18:00",
    "flightNumber": "",
    "passengers": "5",
    "notes": "",
    "status": "Completed",
    "city": "Bafra",
    "address": "Bafra, KKTC",
    "age": "33",
    "language": "English",
    "gender": "Female",
    "id": 1784273076690
  },
  {
    "firstName": "Serkan",
    "lastName": "Öztürk",
    "email": "serkanöztürk@mail.com",
    "phone": "05436046415",
    "company": "Acapulco Resort",
    "customerType": "Hotel Guest",
    "vehicleType": "Executive Sedan",
    "transferType": "Event Logistics",
    "pickupLocation": "Bafra Resort Area",
    "dropoffLocation": "Girne (Kyrenia) City Centre",
    "transferDate": "2026-02-04",
    "transferTime": "02:20",
    "flightNumber": "",
    "passengers": "3",
    "notes": "",
    "status": "Completed",
    "city": "Bafra",
    "address": "Bafra, KKTC",
    "age": "47",
    "language": "Turkish",
    "gender": "Male",
    "id": 1784273076691
  },
  {
    "firstName": "Volkan",
    "lastName": "Öztürk",
    "email": "volkanöztürk@mail.com",
    "phone": "05522106430",
    "company": "Merit Royal Diamond",
    "customerType": "Hotel Guest",
    "vehicleType": "Executive Sedan",
    "transferType": "Intercity Ride",
    "pickupLocation": "Merit Royal Diamond",
    "dropoffLocation": "Güzelyurt (Morphou)",
    "transferDate": "2026-06-18",
    "transferTime": "18:22",
    "flightNumber": "",
    "passengers": "3",
    "notes": "",
    "status": "Cancelled",
    "city": "Merit",
    "address": "Merit, KKTC",
    "age": "59",
    "language": "English",
    "gender": "Male",
    "id": 1784273076692
  },
  {
    "firstName": "Mustafa",
    "lastName": "Özdemir",
    "email": "mustafaözdemir@mail.com",
    "phone": "05389199489",
    "company": "",
    "customerType": "Individual VIP",
    "vehicleType": "VIP Business Van",
    "transferType": "Event Logistics",
    "pickupLocation": "Merit Royal Diamond",
    "dropoffLocation": "Arkın Iskele Hotel",
    "transferDate": "2026-09-12",
    "transferTime": "20:54",
    "flightNumber": "",
    "passengers": "1",
    "notes": "",
    "status": "Confirmed",
    "city": "Merit",
    "address": "Merit, KKTC",
    "age": "46",
    "language": "Turkish",
    "gender": "Male",
    "id": 1784273076693
  },
  {
    "firstName": "Mehmet",
    "lastName": "Doğan",
    "email": "mehmetdoğan@mail.com",
    "phone": "05348608552",
    "company": "",
    "customerType": "Individual VIP",
    "vehicleType": "Executive Sedan",
    "transferType": "Event Logistics",
    "pickupLocation": "İskele (Trikomo)",
    "dropoffLocation": "Girne (Kyrenia) City Centre",
    "transferDate": "2026-11-08",
    "transferTime": "09:09",
    "flightNumber": "",
    "passengers": "5",
    "notes": "Please provide a child seat.",
    "status": "Confirmed",
    "city": "İskele",
    "address": "İskele, KKTC",
    "age": "42",
    "language": "Turkish",
    "gender": "Male",
    "id": 1784273076694
  },
  {
    "firstName": "Ozan",
    "lastName": "Öztürk",
    "email": "ozanöztürk@mail.com",
    "phone": "05426269915",
    "company": "",
    "customerType": "Individual VIP",
    "vehicleType": "Luxury Minibus",
    "transferType": "Airport Transfer",
    "pickupLocation": "Lord's Palace Hotel",
    "dropoffLocation": "Larnaca International Airport",
    "transferDate": "2026-03-14",
    "transferTime": "07:32",
    "flightNumber": "PC 8450",
    "passengers": "4",
    "notes": "Fast track requested at the airport.",
    "status": "Completed",
    "city": "Lord's",
    "address": "Lord's, KKTC",
    "age": "54",
    "language": "Turkish",
    "gender": "Male",
    "id": 1784273076695
  },
  {
    "firstName": "Ceren",
    "lastName": "Yılmaz",
    "email": "cerenyılmaz@mail.com",
    "phone": "05391091719",
    "company": "Kaya Palazzo Resort",
    "customerType": "Hotel Guest",
    "vehicleType": "VIP Business Van",
    "transferType": "Point to Point",
    "pickupLocation": "Gazimağusa (Famagusta) City Centre",
    "dropoffLocation": "Cratos Premium Hotel",
    "transferDate": "2026-06-15",
    "transferTime": "14:00",
    "flightNumber": "",
    "passengers": "4",
    "notes": "",
    "status": "Cancelled",
    "city": "Gazimağusa",
    "address": "Gazimağusa, KKTC",
    "age": "35",
    "language": "Turkish",
    "gender": "Female",
    "id": 1784273076696
  },
  {
    "firstName": "Ahmet",
    "lastName": "Öztürk",
    "email": "ahmetöztürk@mail.com",
    "phone": "05538096389",
    "company": "",
    "customerType": "Individual VIP",
    "vehicleType": "Luxury Minibus",
    "transferType": "Event Logistics",
    "pickupLocation": "Lefkoşa (Nicosia) City Centre",
    "dropoffLocation": "Cratos Premium Hotel",
    "transferDate": "2026-11-06",
    "transferTime": "08:25",
    "flightNumber": "",
    "passengers": "2",
    "notes": "",
    "status": "Confirmed",
    "city": "Lefkoşa",
    "address": "Lefkoşa, KKTC",
    "age": "36",
    "language": "Turkish",
    "gender": "Male",
    "id": 1784273076697
  },
  {
    "firstName": "Ece",
    "lastName": "Doğan",
    "email": "ecedoğan@mail.com",
    "phone": "05315345975",
    "company": "Limak Cyprus Deluxe",
    "customerType": "Hotel Guest",
    "vehicleType": "First Class Sedan",
    "transferType": "Intercity Ride",
    "pickupLocation": "Limak Cyprus Deluxe",
    "dropoffLocation": "Les Ambassadeurs",
    "transferDate": "2026-01-17",
    "transferTime": "21:26",
    "flightNumber": "",
    "passengers": "5",
    "notes": "",
    "status": "Cancelled",
    "city": "Limak",
    "address": "Limak, KKTC",
    "age": "25",
    "language": "English",
    "gender": "Female",
    "id": 1784273076698
  },
  {
    "firstName": "Büşra",
    "lastName": "Şahin",
    "email": "büşraşahin@mail.com",
    "phone": "05461202795",
    "company": "",
    "customerType": "Individual VIP",
    "vehicleType": "VIP Business Van",
    "transferType": "Airport Transfer",
    "pickupLocation": "Ercan International Airport",
    "dropoffLocation": "Kaya Palazzo Resort",
    "transferDate": "2026-10-11",
    "transferTime": "15:47",
    "flightNumber": "TK 8946",
    "passengers": "5",
    "notes": "",
    "status": "Cancelled",
    "city": "Ercan",
    "address": "Ercan, KKTC",
    "age": "39",
    "language": "English",
    "gender": "Female",
    "id": 1784273076699
  },
  {
    "firstName": "Merve",
    "lastName": "Yıldız",
    "email": "merveyıldız@mail.com",
    "phone": "05345894332",
    "company": "Concorde Luxury Resort",
    "customerType": "Hotel Guest",
    "vehicleType": "First Class Sedan",
    "transferType": "Hourly Chauffeur",
    "pickupLocation": "Elexus Hotel Resort",
    "dropoffLocation": "Güzelyurt (Morphou)",
    "transferDate": "2026-11-03",
    "transferTime": "23:06",
    "flightNumber": "",
    "passengers": "1",
    "notes": "",
    "status": "Confirmed",
    "city": "Elexus",
    "address": "Elexus, KKTC",
    "age": "29",
    "language": "Turkish",
    "gender": "Female",
    "id": 1784273076700
  },
  {
    "firstName": "Mehmet",
    "lastName": "Yıldız",
    "email": "mehmetyıldız@mail.com",
    "phone": "05303362514",
    "company": "Les Ambassadeurs",
    "customerType": "Hotel Guest",
    "vehicleType": "First Class Sedan",
    "transferType": "Hourly Chauffeur",
    "pickupLocation": "Long Beach Area",
    "dropoffLocation": "Bafra Resort Area",
    "transferDate": "2026-05-15",
    "transferTime": "12:30",
    "flightNumber": "",
    "passengers": "4",
    "notes": "Guest has extra luggage, please assist.",
    "status": "Completed",
    "city": "Long",
    "address": "Long, KKTC",
    "age": "41",
    "language": "Turkish",
    "gender": "Male",
    "id": 1784273076701
  },
  {
    "firstName": "Hüseyin",
    "lastName": "Arslan",
    "email": "hüseyinarslan@mail.com",
    "phone": "05322254000",
    "company": "",
    "customerType": "Individual VIP",
    "vehicleType": "Executive Sedan",
    "transferType": "Event Logistics",
    "pickupLocation": "İskele (Trikomo)",
    "dropoffLocation": "Lord's Palace Hotel",
    "transferDate": "2026-10-06",
    "transferTime": "17:50",
    "flightNumber": "",
    "passengers": "4",
    "notes": "",
    "status": "Confirmed",
    "city": "İskele",
    "address": "İskele, KKTC",
    "age": "27",
    "language": "Turkish",
    "gender": "Male",
    "id": 1784273076702
  },
  {
    "firstName": "Volkan",
    "lastName": "Yıldız",
    "email": "volkanyıldız@mail.com",
    "phone": "05326805317",
    "company": "Lord's Palace Hotel",
    "customerType": "Hotel Guest",
    "vehicleType": "Premium SUV",
    "transferType": "Hourly Chauffeur",
    "pickupLocation": "Bafra Resort Area",
    "dropoffLocation": "Limak Cyprus Deluxe",
    "transferDate": "2026-02-14",
    "transferTime": "14:26",
    "flightNumber": "",
    "passengers": "4",
    "notes": "",
    "status": "Completed",
    "city": "Bafra",
    "address": "Bafra, KKTC",
    "age": "38",
    "language": "Turkish",
    "gender": "Male",
    "id": 1784273076703
  },
  {
    "firstName": "Pınar",
    "lastName": "Kaya",
    "email": "pınarkaya@mail.com",
    "phone": "05456789987",
    "company": "",
    "customerType": "Individual VIP",
    "vehicleType": "Luxury Minibus",
    "transferType": "Event Logistics",
    "pickupLocation": "Girne (Kyrenia) City Centre",
    "dropoffLocation": "Cratos Premium Hotel",
    "transferDate": "2026-02-23",
    "transferTime": "22:01",
    "flightNumber": "",
    "passengers": "3",
    "notes": "VIP meet and greet at the gate.",
    "status": "Completed",
    "city": "Girne",
    "address": "Girne, KKTC",
    "age": "37",
    "language": "Turkish",
    "gender": "Female",
    "id": 1784273076704
  },
  {
    "firstName": "Can",
    "lastName": "Öztürk",
    "email": "canöztürk@mail.com",
    "phone": "05419715131",
    "company": "",
    "customerType": "Individual VIP",
    "vehicleType": "Luxury Minibus",
    "transferType": "Event Logistics",
    "pickupLocation": "Bafra Resort Area",
    "dropoffLocation": "Lord's Palace Hotel",
    "transferDate": "2026-11-15",
    "transferTime": "14:35",
    "flightNumber": "",
    "passengers": "1",
    "notes": "",
    "status": "Confirmed",
    "city": "Bafra",
    "address": "Bafra, KKTC",
    "age": "57",
    "language": "English",
    "gender": "Male",
    "id": 1784273076705
  },
  {
    "firstName": "Ozan",
    "lastName": "Şahin",
    "email": "ozanşahin@mail.com",
    "phone": "05323162308",
    "company": "",
    "customerType": "Individual VIP",
    "vehicleType": "Premium SUV",
    "transferType": "Hourly Chauffeur",
    "pickupLocation": "Limak Cyprus Deluxe",
    "dropoffLocation": "Girne (Kyrenia) City Centre",
    "transferDate": "2026-06-10",
    "transferTime": "02:47",
    "flightNumber": "",
    "passengers": "4",
    "notes": "VIP meet and greet at the gate.",
    "status": "Completed",
    "city": "Limak",
    "address": "Limak, KKTC",
    "age": "22",
    "language": "English",
    "gender": "Male",
    "id": 1784273076706
  },
  {
    "firstName": "Gizem",
    "lastName": "Demir",
    "email": "gizemdemir@mail.com",
    "phone": "05471512009",
    "company": "",
    "customerType": "Individual VIP",
    "vehicleType": "Luxury Minibus",
    "transferType": "Event Logistics",
    "pickupLocation": "Girne (Kyrenia) City Centre",
    "dropoffLocation": "Kaya Palazzo Resort",
    "transferDate": "2026-08-01",
    "transferTime": "20:07",
    "flightNumber": "",
    "passengers": "4",
    "notes": "Guest has extra luggage, please assist.",
    "status": "Confirmed",
    "city": "Girne",
    "address": "Girne, KKTC",
    "age": "21",
    "language": "English",
    "gender": "Female",
    "id": 1784273076707
  },
  {
    "firstName": "Ece",
    "lastName": "Öztürk",
    "email": "eceöztürk@mail.com",
    "phone": "05564955003",
    "company": "",
    "customerType": "Individual VIP",
    "vehicleType": "Executive Sedan",
    "transferType": "Hourly Chauffeur",
    "pickupLocation": "Girne (Kyrenia) City Centre",
    "dropoffLocation": "İskele (Trikomo)",
    "transferDate": "2026-11-21",
    "transferTime": "07:43",
    "flightNumber": "",
    "passengers": "5",
    "notes": "",
    "status": "Cancelled",
    "city": "Girne",
    "address": "Girne, KKTC",
    "age": "46",
    "language": "English",
    "gender": "Female",
    "id": 1784273076708
  },
  {
    "firstName": "Emre",
    "lastName": "Aydın",
    "email": "emreaydın@mail.com",
    "phone": "05516438425",
    "company": "",
    "customerType": "Individual VIP",
    "vehicleType": "VIP Business Van",
    "transferType": "Event Logistics",
    "pickupLocation": "Lefkoşa (Nicosia) City Centre",
    "dropoffLocation": "Bafra Resort Area",
    "transferDate": "2026-07-09",
    "transferTime": "16:21",
    "flightNumber": "",
    "passengers": "5",
    "notes": "",
    "status": "Completed",
    "city": "Lefkoşa",
    "address": "Lefkoşa, KKTC",
    "age": "49",
    "language": "English",
    "gender": "Male",
    "id": 1784273076709
  },
  {
    "firstName": "Volkan",
    "lastName": "Kaya",
    "email": "volkankaya@mail.com",
    "phone": "05467038167",
    "company": "",
    "customerType": "Individual VIP",
    "vehicleType": "Executive Sedan",
    "transferType": "Event Logistics",
    "pickupLocation": "Kaya Palazzo Resort",
    "dropoffLocation": "Merit Royal Diamond",
    "transferDate": "2026-06-17",
    "transferTime": "19:44",
    "flightNumber": "",
    "passengers": "1",
    "notes": "",
    "status": "Completed",
    "city": "Kaya",
    "address": "Kaya, KKTC",
    "age": "35",
    "language": "English",
    "gender": "Male",
    "id": 1784273076710
  },
  {
    "firstName": "Merve",
    "lastName": "Kaya",
    "email": "mervekaya@mail.com",
    "phone": "05371221772",
    "company": "",
    "customerType": "Individual VIP",
    "vehicleType": "Premium SUV",
    "transferType": "Airport Transfer",
    "pickupLocation": "Arkın Iskele Hotel",
    "dropoffLocation": "Larnaca International Airport",
    "transferDate": "2026-10-06",
    "transferTime": "23:59",
    "flightNumber": "PC 1299",
    "passengers": "3",
    "notes": "",
    "status": "Confirmed",
    "city": "Arkın",
    "address": "Arkın, KKTC",
    "age": "58",
    "language": "Turkish",
    "gender": "Female",
    "id": 1784273076711
  },
  {
    "firstName": "Gizem",
    "lastName": "Doğan",
    "email": "gizemdoğan@mail.com",
    "phone": "05586837637",
    "company": "",
    "customerType": "Individual VIP",
    "vehicleType": "VIP Business Van",
    "transferType": "Intercity Ride",
    "pickupLocation": "Bafra Resort Area",
    "dropoffLocation": "İskele (Trikomo)",
    "transferDate": "2026-04-26",
    "transferTime": "07:53",
    "flightNumber": "",
    "passengers": "4",
    "notes": "",
    "status": "Completed",
    "city": "Bafra",
    "address": "Bafra, KKTC",
    "age": "40",
    "language": "Turkish",
    "gender": "Female",
    "id": 1784273076712
  },
  {
    "firstName": "Aslı",
    "lastName": "Öztürk",
    "email": "aslıöztürk@mail.com",
    "phone": "05341573939",
    "company": "",
    "customerType": "Individual VIP",
    "vehicleType": "VIP Business Van",
    "transferType": "Hourly Chauffeur",
    "pickupLocation": "Kaya Palazzo Resort",
    "dropoffLocation": "Limak Cyprus Deluxe",
    "transferDate": "2026-10-25",
    "transferTime": "00:11",
    "flightNumber": "",
    "passengers": "1",
    "notes": "Please provide a child seat.",
    "status": "Cancelled",
    "city": "Kaya",
    "address": "Kaya, KKTC",
    "age": "55",
    "language": "English",
    "gender": "Female",
    "id": 1784273076713
  },
  {
    "firstName": "Defne ",
    "lastName": "Katalbaş",
    "email": "defnekatalbas@mail.com",
    "phone": "06726720672",
    "company": "",
    "customerType": "Individual VIP",
    "vehicleType": "Luxury Minibus",
    "transferType": "Airport Transfer",
    "pickupLocation": "Ercan International Airport",
    "dropoffLocation": "İskele (Trikomo)",
    "transferDate": "2026-10-02",
    "transferTime": "05:15",
    "flightNumber": "TK 1926",
    "passengers": "3",
    "notes": "",
    "status": "Confirmed",
    "city": "Gazimağusa",
    "address": "Gazimağusa, KKTC",
    "age": "43",
    "language": "Turkish",
    "gender": "Female",
    "id": 1784700265087
  },
  {
    "firstName": "Defne ",
    "lastName": "Katalbaş",
    "email": "defnekatalbas@mail.com",
    "phone": "06726720672",
    "company": "",
    "customerType": "Individual VIP",
    "vehicleType": "Executive Sedan",
    "transferType": "Airport Transfer",
    "pickupLocation": "Ercan International Airport",
    "dropoffLocation": "İskele (Trikomo)",
    "transferDate": "2026-04-11",
    "transferTime": "17:20",
    "flightNumber": "TK 1926",
    "passengers": "3",
    "notes": "",
    "status": "Completed",
    "city": "Gazimağusa",
    "address": "Gazimağusa, KKTC",
    "age": "43",
    "language": "Turkish",
    "gender": "Female",
    "id": 1784700265088
  },
  {
    "firstName": "Alpay",
    "lastName": "Fah",
    "email": "alpayfah@mail.com",
    "phone": "03113110311",
    "company": "",
    "customerType": "Individual VIP",
    "vehicleType": "Executive Sedan",
    "transferType": "Hourly Chauffeur",
    "pickupLocation": "Girne (Kyrenia) City Centre",
    "dropoffLocation": "Lefkoşa (Nicosia) City Centre",
    "transferDate": "2026-05-16",
    "transferTime": "08:07",
    "flightNumber": "",
    "passengers": "",
    "notes": "",
    "status": "Completed",
    "city": "Girne",
    "address": "Girne, KKTC",
    "age": "44",
    "language": "Greek",
    "gender": "Male",
    "id": 1784700265089
  },
  {
    "firstName": "Alpay",
    "lastName": "Fah",
    "email": "alpayfah@mail.com",
    "phone": "03113110311",
    "company": "",
    "customerType": "Individual VIP",
    "vehicleType": "Premium SUV",
    "transferType": "Hourly Chauffeur",
    "pickupLocation": "Girne (Kyrenia) City Centre",
    "dropoffLocation": "Lefkoşa (Nicosia) City Centre",
    "transferDate": "2026-01-06",
    "transferTime": "14:42",
    "flightNumber": "",
    "passengers": "",
    "notes": "",
    "status": "Completed",
    "city": "Girne",
    "address": "Girne, KKTC",
    "age": "44",
    "language": "Greek",
    "gender": "Male",
    "id": 1784700265090
  },
  {
    "firstName": "İbrahim Halil",
    "lastName": "Yarık",
    "email": "halilyarik@mail.com",
    "phone": "09879870987",
    "company": "",
    "customerType": "Individual VIP",
    "vehicleType": "First Class Sedan",
    "transferType": "Point to Point",
    "pickupLocation": "Ercan International Airport",
    "dropoffLocation": "Lefkoşa (Nicosia) City Centre",
    "transferDate": "2026-01-20",
    "transferTime": "03:24",
    "flightNumber": "",
    "passengers": "2",
    "notes": "Please provide a child seat.",
    "status": "Completed",
    "city": "İskele",
    "address": "İskele, KKTC",
    "age": "46",
    "language": "Turkish",
    "gender": "Male",
    "id": 1784700265091
  },
  {
    "firstName": "Vedat",
    "lastName": "Dozkıran",
    "email": "vedatdozkiran@mail.com",
    "phone": "04444440444",
    "company": "",
    "customerType": "Individual VIP",
    "vehicleType": "First Class Sedan",
    "transferType": "Point to Point",
    "pickupLocation": "İskele (Trikomo)",
    "dropoffLocation": "Lefkoşa (Nicosia) City Centre",
    "transferDate": "2026-08-21",
    "transferTime": "03:21",
    "flightNumber": "",
    "passengers": "",
    "notes": "Do not ring the bell upon arrival.",
    "status": "Confirmed",
    "city": "Lefkoşa",
    "address": "Lefkoşa, KKTC",
    "age": "32",
    "language": "English",
    "gender": "Male",
    "id": 1784700265092
  },
  {
    "firstName": "Arda",
    "lastName": "Kahin",
    "email": "ardakahin@mail.com",
    "phone": "05425420542",
    "company": "",
    "customerType": "Individual VIP",
    "vehicleType": "Premium SUV",
    "transferType": "Hourly Chauffeur",
    "pickupLocation": "Ercan International Airport",
    "dropoffLocation": "Girne (Kyrenia) City Centre",
    "transferDate": "2026-07-21",
    "transferTime": "19:16",
    "flightNumber": "",
    "passengers": "2",
    "notes": "",
    "status": "Completed",
    "city": "Girne",
    "address": "Girne, KKTC",
    "age": "23",
    "language": "Turkish",
    "gender": "Male",
    "id": 1784700265093
  },
  {
    "firstName": "Ahmet",
    "lastName": "Çelik",
    "email": "ahmetçelik@mail.com",
    "phone": "05368515052",
    "company": "",
    "customerType": "Individual VIP",
    "vehicleType": "First Class Sedan",
    "transferType": "Intercity Ride",
    "pickupLocation": "İskele (Trikomo)",
    "dropoffLocation": "Long Beach Area",
    "transferDate": "2026-11-08",
    "transferTime": "15:13",
    "flightNumber": "",
    "passengers": "1",
    "notes": "",
    "status": "Confirmed",
    "city": "İskele",
    "address": "İskele, KKTC",
    "age": "40",
    "language": "Turkish",
    "gender": "Male",
    "id": 1784700265094
  },
  {
    "firstName": "Fatma",
    "lastName": "Doğan",
    "email": "fatmadoğan@mail.com",
    "phone": "05455316574",
    "company": "",
    "customerType": "Individual VIP",
    "vehicleType": "Premium SUV",
    "transferType": "Hourly Chauffeur",
    "pickupLocation": "Concorde Luxury Resort",
    "dropoffLocation": "Cratos Premium Hotel",
    "transferDate": "2026-11-25",
    "transferTime": "17:58",
    "flightNumber": "",
    "passengers": "2",
    "notes": "",
    "status": "Confirmed",
    "city": "Concorde",
    "address": "Concorde, KKTC",
    "age": "22",
    "language": "Turkish",
    "gender": "Female",
    "id": 1784700265095
  },
  {
    "firstName": "Fatma",
    "lastName": "Doğan",
    "email": "fatmadoğan@mail.com",
    "phone": "05455316574",
    "company": "",
    "customerType": "Individual VIP",
    "vehicleType": "Premium SUV",
    "transferType": "Hourly Chauffeur",
    "pickupLocation": "Concorde Luxury Resort",
    "dropoffLocation": "Cratos Premium Hotel",
    "transferDate": "2026-08-20",
    "transferTime": "17:29",
    "flightNumber": "",
    "passengers": "2",
    "notes": "",
    "status": "Confirmed",
    "city": "Concorde",
    "address": "Concorde, KKTC",
    "age": "22",
    "language": "Turkish",
    "gender": "Female",
    "id": 1784700265096
  },
  {
    "firstName": "Volkan",
    "lastName": "Çelik",
    "email": "volkançelik@mail.com",
    "phone": "05445429128",
    "company": "",
    "customerType": "Individual VIP",
    "vehicleType": "VIP Business Van",
    "transferType": "Airport Transfer",
    "pickupLocation": "Lord's Palace Hotel",
    "dropoffLocation": "Ercan International Airport",
    "transferDate": "2026-02-08",
    "transferTime": "18:02",
    "flightNumber": "TK 6513",
    "passengers": "4",
    "notes": "",
    "status": "Completed",
    "city": "Lord's",
    "address": "Lord's, KKTC",
    "age": "52",
    "language": "English",
    "gender": "Male",
    "id": 1784700265097
  },
  {
    "firstName": "Asrın",
    "lastName": "Şahin",
    "email": "asrinsahin@mail.com",
    "phone": "08878878787",
    "company": "",
    "customerType": "Individual VIP",
    "vehicleType": "First Class Sedan",
    "transferType": "Airport Transfer",
    "pickupLocation": "Ercan International Airport",
    "dropoffLocation": "Girne (Kyrenia) City Centre",
    "transferDate": "2026-07-30",
    "transferTime": "08:00",
    "flightNumber": "TK 990",
    "passengers": "2",
    "notes": "Champagne required",
    "status": "Cancelled",
    "id": 1784715682463,
    "createdAt": "22 Jul 2026"
  },
  {
    "firstName": "Asrın",
    "lastName": "Şahin",
    "email": "asrinsahin@mail.com",
    "phone": "08878878787",
    "company": "",
    "customerType": "Individual VIP",
    "vehicleType": "First Class Sedan",
    "transferType": "Airport Transfer",
    "pickupLocation": "Girne (Kyrenia) City Centre",
    "dropoffLocation": "Ercan International Airport",
    "transferDate": "2026-07-31",
    "transferTime": "04:00",
    "flightNumber": "TK 960",
    "passengers": "2",
    "notes": "",
    "status": "Confirmed",
    "id": 1784716342337,
    "createdAt": "22 Jul 2026"
  },
  {
    "firstName": "Asrın",
    "lastName": "Şahin",
    "email": "asrinsahin@mail.com",
    "phone": "08878878787",
    "company": "Merit Royal Diamond",
    "customerType": "Hotel Guest",
    "vehicleType": "Executive Sedan",
    "transferType": "Airport Transfer",
    "pickupLocation": "Merit Royal Diamond",
    "dropoffLocation": "Gazimağusa (Famagusta) City Centre",
    "transferDate": "2026-07-18",
    "transferTime": "18:00",
    "flightNumber": "",
    "passengers": "1",
    "notes": "",
    "status": "Completed",
    "id": 1784716445819,
    "createdAt": "22 Jul 2026"
  }
]